savings_rate.py
MMM_Savings_Rate-0.2.data/scripts/sr_launcher.py
MMM_Savings_Rate-0.2.dist-info/DESCRIPTION.rst
MMM_Savings_Rate-0.2.dist-info/METADATA
MMM_Savings_Rate-0.2.dist-info/RECORD
MMM_Savings_Rate-0.2.dist-info/WHEEL
MMM_Savings_Rate-0.2.dist-info/entry_points.txt
MMM_Savings_Rate-0.2.dist-info/metadata.json
MMM_Savings_Rate-0.2.dist-info/top_level.txt
