Metadata-Version: 2.0
Name: MMM-Savings-Rate
Version: 0.2
Summary: An application that can parse spreadsheets in order to calculate and plot a user's monthly savings rate over time. 
Home-page: https://github.com/bbusenius/MMM_Savings_Rate.git
Author: Brad Busenius
Author-email: bbusenius@gmail.com
License: GNU GPLv3, see LICENSE.txt
Platform: UNKNOWN
Requires-Dist: bokeh
Requires-Dist: certifi
Requires-Dist: diablo-python
Requires-Dist: keyring
Requires-Dist: mintapi
Requires-Dist: python-dateutil
